qdecomp/__init__.py
qdecomp/decompositions/__init__.py
qdecomp/decompositions/circuit.py
qdecomp/decompositions/common_gate_decompositions.py
qdecomp/decompositions/sqg.py
qdecomp/decompositions/tqg.py
qdecomp/plot/__init__.py
qdecomp/plot/plot_grid_problem.py
qdecomp/plot/plot_steiner_ellipse.py
qdecomp/rings/__init__.py
qdecomp/rings/rings.py
qdecomp/utils/__init__.py
qdecomp/utils/gates.py
qdecomp/utils/gates_utils.py
qdecomp/utils/qgate.py
qdecomp/utils/steiner_ellipse.py
qdecomp/utils/diophantine/__init__.py
qdecomp/utils/diophantine/diophantine_equation.py
qdecomp/utils/diophantine/tonelli_shanks.py
qdecomp/utils/exact_synthesis/__init__.py
qdecomp/utils/exact_synthesis/exact_synthesis.py
qdecomp/utils/exact_synthesis/s3_generator.py
qdecomp/utils/exact_synthesis/s3_table.json
qdecomp/utils/grid_problem/__init__.py
qdecomp/utils/grid_problem/grid_algorithms.py
qdecomp/utils/grid_problem/grid_operator.py
qdecomp/utils/grid_problem/grid_problem.py
qdecomp/utils/grid_problem/rz_approx.py
qdecomp/utils/grid_problem/state.py
qdecomp-1.0.1.dist-info/licenses/LICENSE
qdecomp-1.0.1.dist-info/METADATA
qdecomp-1.0.1.dist-info/WHEEL
qdecomp-1.0.1.dist-info/top_level.txt
qdecomp-1.0.1.dist-info/RECORD
