Metadata-Version: 2.4
Name: qdecomp
Version: 1.0.1
Summary: Clifford+T quantum gate compiler.
Author-email: Francis Blais <francis.blais@polymtl.ca>, Marius Trudeau <marius.trudeau@polymtl.ca>, Olivier Romain <olivier.romain@polymtl.ca>, Vincent Girouard <vincent-2.girouard@polymtl.ca>
License-Expression: Apache-2.0
Project-URL: Homepage, https://github.com/polyquantique/QDecomp
Project-URL: Documentation, https://qdecomp.readthedocs.io/en/latest/
Project-URL: Issues, https://github.com/polyquantique/QDecomp/issues
Keywords: quantum,decomposition,python,compiler,clifford+t,quantum-computing,quantum-circuits
Classifier: Programming Language :: Python
Classifier: Programming Language :: Python :: 3
Classifier: Programming Language :: Python :: 3.9
Classifier: Programming Language :: Python :: 3.10
Classifier: Programming Language :: Python :: 3.11
Classifier: Programming Language :: Python :: 3.12
Classifier: Programming Language :: Python :: 3.13
Classifier: Programming Language :: Python :: 3.14
Classifier: Operating System :: OS Independent
Classifier: Topic :: Scientific/Engineering
Classifier: Topic :: Scientific/Engineering :: Quantum Computing
Requires-Python: >=3.9
License-File: LICENSE
Requires-Dist: numpy>=2.0.2
Requires-Dist: mpmath>=1.3.0
Requires-Dist: scipy
Requires-Dist: matplotlib
Provides-Extra: dev
Requires-Dist: pytest>=8.3.3; extra == "dev"
Requires-Dist: pytest-cov; extra == "dev"
Requires-Dist: black; extra == "dev"
Requires-Dist: isort; extra == "dev"
Requires-Dist: sympy; extra == "dev"
Dynamic: license-file
